deeporigin_data/__init__.py
deeporigin_data/_base_client.py
deeporigin_data/_client.py
deeporigin_data/_compat.py
deeporigin_data/_constants.py
deeporigin_data/_exceptions.py
deeporigin_data/_files.py
deeporigin_data/_models.py
deeporigin_data/_qs.py
deeporigin_data/_resource.py
deeporigin_data/_response.py
deeporigin_data/_streaming.py
deeporigin_data/_types.py
deeporigin_data/_version.py
deeporigin_data/py.typed
deeporigin_data/_utils/__init__.py
deeporigin_data/_utils/_logs.py
deeporigin_data/_utils/_proxy.py
deeporigin_data/_utils/_reflection.py
deeporigin_data/_utils/_resources_proxy.py
deeporigin_data/_utils/_streams.py
deeporigin_data/_utils/_sync.py
deeporigin_data/_utils/_transform.py
deeporigin_data/_utils/_typing.py
deeporigin_data/_utils/_utils.py
deeporigin_data/lib/.keep
deeporigin_data/resources/__init__.py
deeporigin_data/types/__init__.py
deeporigin_data/types/add_database_column_response.py
deeporigin_data/types/chat_create_thread_response.py
deeporigin_data/types/chat_list_messages_response.py
deeporigin_data/types/client_add_database_column_params.py
deeporigin_data/types/client_archive_files_params.py
deeporigin_data/types/client_chat_create_thread_params.py
deeporigin_data/types/client_chat_list_messages_params.py
deeporigin_data/types/client_chat_send_message_params.py
deeporigin_data/types/client_configure_column_select_options_params.py
deeporigin_data/types/client_convert_id_format_params.py
deeporigin_data/types/client_create_database_params.py
deeporigin_data/types/client_create_file_download_url_params.py
deeporigin_data/types/client_create_file_upload_params.py
deeporigin_data/types/client_create_workspace_params.py
deeporigin_data/types/client_delete_database_column_params.py
deeporigin_data/types/client_delete_database_params.py
deeporigin_data/types/client_delete_rows_params.py
deeporigin_data/types/client_delete_workspace_params.py
deeporigin_data/types/client_describe_code_execution_params.py
deeporigin_data_sdk-0.1.0a73.dist-info/METADATA
deeporigin_data_sdk-0.1.0a73.dist-info/WHEEL
deeporigin_data_sdk-0.1.0a73.dist-info/licenses/LICENSE
deeporigin_data_sdk-0.1.0a73.dist-info/RECORD
